Redframe_hello/__init__.py
Redframe_hello/main.py
Redframe_hello-0.0.5.dist-info/METADATA
Redframe_hello-0.0.5.dist-info/WHEEL
Redframe_hello-0.0.5.dist-info/entry_points.txt
Redframe_hello-0.0.5.dist-info/top_level.txt
Redframe_hello-0.0.5.dist-info/RECORD
