Metadata-Version: 2.1
Name: Redframe_hello
Version: 0.0.5
Summary: This is a example project to demonstrate how to create a Python package and publish it to PyPI by Redframe
Classifier: Programming Language :: Python :: 3
Classifier: License :: OSI Approved :: MIT License
Classifier: Operating System :: OS Independent
